dictum_core/__init__.py
dictum_core/backends/__init__.py
dictum_core/backends/base.py
dictum_core/backends/mixins/__init__.py
dictum_core/backends/mixins/arithmetic.py
dictum_core/backends/mixins/datediff.py
dictum_core/backends/pandas.py
dictum_core/backends/secret.py
dictum_core/backends/sql_alchemy.py
dictum_core/backends/sqlite.py
dictum_core/engine/__init__.py
dictum_core/engine/aggregate_query_builder.py
dictum_core/engine/checks.py
dictum_core/engine/computation.py
dictum_core/engine/engine.py
dictum_core/engine/metrics.py
dictum_core/engine/operators.py
dictum_core/engine/result.py
dictum_core/examples/__init__.py
dictum_core/examples/chinook/__init__.py
dictum_core/examples/chinook/chinook.postgres.sql
dictum_core/examples/chinook/chinook.sqlite.sql
dictum_core/examples/chinook/generate.py
dictum_core/examples/chinook/metrics/media/avg_track_length.yml
dictum_core/examples/chinook/metrics/media/avg_track_price.yml
dictum_core/examples/chinook/metrics/media/revenue_per_track.yml
dictum_core/examples/chinook/metrics/media/track_count.yml
dictum_core/examples/chinook/metrics/media/track_length.yml
dictum_core/examples/chinook/metrics/orders/arppu.yml
dictum_core/examples/chinook/metrics/orders/avg_sold_unit_price.yml
dictum_core/examples/chinook/metrics/orders/items_sold.yml
dictum_core/examples/chinook/metrics/orders/music_revenue.yml
dictum_core/examples/chinook/metrics/orders/music_tracks_sold.yml
dictum_core/examples/chinook/metrics/orders/pct_music_orders.yml
dictum_core/examples/chinook/metrics/orders/revenue.yml
dictum_core/examples/chinook/metrics/orders/unique_paying_customers.yml
dictum_core/examples/chinook/metrics/people/n_customers.yml
dictum_core/examples/chinook/metrics/people/n_employees.yml
dictum_core/examples/chinook/profiles.yml
dictum_core/examples/chinook/project.yml
dictum_core/examples/chinook/tables/albums.yml
dictum_core/examples/chinook/tables/artists.yml
dictum_core/examples/chinook/tables/customers.yml
dictum_core-0.1.15.dist-info/METADATA
dictum_core-0.1.15.dist-info/WHEEL
dictum_core-0.1.15.dist-info/entry_points.txt
dictum_core-0.1.15.dist-info/RECORD
