Metadata-Version: 2.1
Name: dictum-core
Version: 0.1.15
Summary: Core library for Dictum
Author: Mikhail Akimov
Requires-Python: >=3.9,<3.13
Classifier: Programming Language :: Python :: 3
Classifier: Programming Language :: Python :: 3.9
Classifier: Programming Language :: Python :: 3.10
Classifier: Programming Language :: Python :: 3.11
Classifier: Programming Language :: Python :: 3.12
Requires-Dist: Babel (>=2.9.1,<3.0.0)
Requires-Dist: Jinja2 (>=3.0.1,<4.0.0)
Requires-Dist: PyYAML (>=6.0.1,<7.0.0)
Requires-Dist: SQLAlchemy (>=2.0.23,<3.0.0)
Requires-Dist: graphlib_backport (>=1.0.3,<2.0.0) ; python_version < "3.9"
Requires-Dist: jupyter (>=1.0.0,<2.0.0)
Requires-Dist: lark (>=1.1.8,<2.0.0)
Requires-Dist: pandas (>=2.1.2,<3.0.0)
Requires-Dist: pydantic (==2.4.2)
Requires-Dist: sqlparse (>=0.4.2,<0.5.0)
Requires-Dist: toolz (>=0.12.0,<0.13.0)
